{
  "Image": "Amoebeye",
  "Name": "Amoebeye",
  "Types": [
    "NPC"
  ],
  "MaxLife": 300,
  "Defense": 60,
  "KBResist": 0.25,
  "Immunities": [
    "<a is=a-link href=https://terraria.wiki.gg/wiki/Poisoned>Poisoned</a>",
    "<a is=a-link href=https://terraria.wiki.gg/wiki/Ichor>Ichor</a>",
    "<a is=a-link image=$fromStats>Torn</a>"
  ],
  "Coins": 5000.0,
  "Drops": [
    {
      "Name": "Bud Barnacle",
      "Chance": "33.333%"
    },
    {
      "Name": "Alkahest",
      "Amount": "2‒5"
    }
  ],
  "RivenAssimilation": 0.04,
  "Expert": {
    "MaxLife": 600,
    "KBResist": 0.32500005,
    "Coins": 12500.0,
    "Drops": [
      {
        "Name": "Bud Barnacle",
        "Chance": "33.333%"
      },
      {
        "Name": "Alkahest",
        "Amount": "2‒5"
      }
    ],
    "RivenAssimilation": 0.051999997
  },
  "Master": {
    "MaxLife": 900,
    "KBResist": 0.39999998,
    "Coins": 12500.0,
    "Drops": [
      {
        "Name": "Bud Barnacle",
        "Chance": "33.333%"
      },
      {
        "Name": "Alkahest",
        "Amount": "2‒5"
      }
    ],
    "RivenAssimilation": 0.06
  },
  "Environment": [
    "<a is=a-link image=$fromStats>Riven Hive</a>",
    "<a is=a-link image=$fromStats>Underground Riven Hive</a>"
  ],
  "BestiaryQuotation": "Amoebeyes are the next evolutionary step for Riven Protoforms ever since the Riven's expansion. They safeguard the hives to eliminate any threats to the ecosystem.",
  "SpriteWidth": 72,
  "InternalName": "Amoebeye"
}