{
  "Image": "§ModImage§/Items/Weapons/Ranged/Blotopus",
  "Name": "Blotopus",
  "Types": [
    "Item",
    "Gun",
    "Weapon"
  ],
  "Damage": 4,
  "DamageClass": "Ranged",
  "Crit": 11,
  "UseTime": 6,
  "Velocity": 7.0,
  "Tooltip": [
    "Fires a stream of needles that bleed enemies",
    "20% chance not consume ammo"
  ],
  "Rarity": "Blue",
  "Sell": 10000,
  "Source": "<a is=a-link href=\"https://terraria.wiki.gg/wiki/Purple_Clubberfish\">Purple Clubberfish</a> (@ <a is=a-link href=https://terraria.wiki.gg/wiki/Shimmer>Shimmer</a>)",
  "Recipes": [
    {
      "stations": [
        "<a is=a-link href=\"https://terraria.wiki.gg/wiki/By_Hand\">By Hand</a>",
        "<a is=a-link href=Shimmer>Shimmer Transmutation</a>"
      ],
      "items": [
        {
          "result": "<a is=a-link image=$fromStats>Blotopus</a>",
          "ingredients": [
            "<a is=a-link href=\"https://terraria.wiki.gg/wiki/Purple_Clubberfish\">Purple Clubberfish</a>"
          ]
        }
      ]
    }
  ],
  "UsedIn": [
    {
      "stations": [
        "<a is=a-link href=\"https://terraria.wiki.gg/wiki/By_Hand\">By Hand</a>",
        "<a is=a-link href=Shimmer>Shimmer Transmutation</a>"
      ],
      "items": [
        {
          "result": "<a is=a-link image=$fromStats>Manasynk</a>",
          "ingredients": [
            "<a is=a-link image=$fromStats>Blotopus</a>"
          ]
        }
      ]
    }
  ],
  "SpriteWidth": 64,
  "InternalName": "Blotopus"
}