{
  "Name": "Defiled Campfire",
  "Types": [
    "Item",
    "Tile"
  ],
  "PlacementSize": [
    3,
    2
  ],
  "UseTime": 10,
  "Rarity": "White",
  "Source": "(10) <a is=a-link href=\"https://terraria.wiki.gg/wiki/Wood\">Wood</a> + (5) <a is=a-link image=$fromStats imageOnly>Defiled Torch</a> (@ <a is=a-link href=\"https://terraria.wiki.gg/wiki/By_Hand\">By Hand</a>)",
  "Recipes": [
    {
      "stations": [
        "<a is=a-link href=\"https://terraria.wiki.gg/wiki/By_Hand\">By Hand</a>"
      ],
      "items": [
        {
          "result": "<a is=a-link image=$fromStats>Defiled Campfire</a>",
          "ingredients": [
            "<a is=a-link image=\"RecipeGroups/Wood\" href=Recipe_Groups>Any Wood</a> (10)",
            "<a is=a-link image=$fromStats>Defiled Torch</a> (5)"
          ]
        }
      ]
    }
  ],
  "SpriteWidth": 30,
  "InternalName": "Defiled_Campfire_Item",
  "Images": [
    "§ModImage§/Tiles/Defiled/Defiled_Campfire_Item",
    "Tiles/Defiled_Campfire"
  ]
}