{
  "Name": "Endowood Toilet",
  "Types": [
    "Item",
    "Tile"
  ],
  "PlacementSize": [
    1,
    2
  ],
  "UseTime": 10,
  "Rarity": "White",
  "Sell": 30,
  "Source": "6<a is=a-link image=$fromStats imageOnly>Endowood</a>(@<a is=a-link href=\"https://terraria.wiki.gg/wiki/Sawmill\">Sawmill</a>)",
  "Recipes": [
    {
      "stations": [
        "<a is=a-link href=\"https://terraria.wiki.gg/wiki/Sawmill\">Sawmill</a>"
      ],
      "items": [
        {
          "result": "<a is=a-link image=$fromStats>Endowood Toilet</a>",
          "ingredients": [
            "<a is=a-link image=$fromStats>Endowood</a> (6)"
          ]
        }
      ]
    }
  ],
  "SpriteWidth": 16,
  "InternalName": "Endowood_Toilet_Item",
  "Images": [
    "§ModImage§/Tiles/Endowood/Endowood_Toilet_Item",
    "Tiles/Endowood_Toilet"
  ]
}