{
  "Image": "§ModImage§/Items/Accessories/Slag_Bucket_Uncursed",
  "Name": "Slag Bucket",
  "Types": [
    "Item",
    "Combat",
    "Accessory",
    "Hardmode"
  ],
  "Defense": 6,
  "Tooltip": [
    "5% damage reduction and slightly increased life regeneration",
    "Grants immunity to knockback, fire blocks, and impeding shrapnel",
    "67% of damage received is redirected to 3 enemies",
    "You regenerate life while on fire"
  ],
  "Rarity": "LightRed",
  "Sell": 20000,
  "Source": " <a is=a-link image=$fromStats imageOnly>Slag Bucket (Cursed)</a> (@ <a is=a-link href=\"https://terraria.wiki.gg/wiki/Bewitching_Table\">Bewitching Table</a>)<div class=divider></div> <a is=a-link image=$fromStats imageOnly>Scrap Barrier</a> +  <a is=a-link image=$fromStats imageOnly>Shield of Retribution</a> (@ <a is=a-link href=\"https://terraria.wiki.gg/wiki/Tinkerer's_Workshop\">Tinkerer's Workshop</a>)",
  "Recipes": [
    {
      "stations": [
        "<a is=a-link href=\"https://terraria.wiki.gg/wiki/Bewitching_Table\">Bewitching Table</a>"
      ],
      "items": [
        {
          "result": "<a is=a-link image=$fromStats>Slag Bucket</a>",
          "ingredients": [
            "<a is=a-link image=$fromStats>Slag Bucket (Cursed)</a>"
          ]
        }
      ]
    },
    {
      "stations": [
        "<a is=a-link href=\"https://terraria.wiki.gg/wiki/Tinkerer's_Workshop\">Tinkerer's Workshop</a>"
      ],
      "items": [
        {
          "result": "<a is=a-link image=$fromStats>Slag Bucket</a>",
          "ingredients": [
            "<a is=a-link image=$fromStats>Scrap Barrier</a>",
            "<a is=a-link image=$fromStats>Shield of Retribution</a>"
          ]
        }
      ]
    }
  ],
  "SpriteWidth": 36,
  "InternalName": "Slag_Bucket_Uncursed"
}