{
  "Image": "§ModImage§/NPCs/Riven/Spider_Amoeba",
  "Name": "Spider Amoeba",
  "Types": [
    "NPC"
  ],
  "MaxLife": 81,
  "Defense": 10,
  "KBResist": 0.5,
  "Immunities": [
    "`[link Torn | $fromStats | $default]`"
  ],
  "Coins": 90.0,
  "Drops": [],
  "Expert": {
    "MaxLife": 178,
    "KBResist": 0.595,
    "Coins": 180.0,
    "Drops": []
  },
  "Master": {
    "MaxLife": 267,
    "KBResist": 0.67999995,
    "Coins": 180.0,
    "Drops": []
  },
  "SpriteWidth": 72,
  "InternalName": "Spider_Amoeba"
}