{
  "Image": "§ModImage§/NPCs/ICARUS/Swarmer",
  "Name": "Swarmer",
  "Types": [
    "NPC"
  ],
  "MaxLife": 80,
  "Defense": 3,
  "Immunities": [
    "`<a is="a-link" href="$default">Confused</a>`",
    "`<a is="a-link" image="$fromStats" href="$default">Stunned</a>`"
  ],
  "Drops": [],
  "Expert": {
    "MaxLife": 160,
    "KBResist": 0.100000024,
    "Coins": 0.0,
    "Drops": []
  },
  "Master": {
    "MaxLife": 240,
    "KBResist": 0.19999999,
    "Coins": 0.0,
    "Drops": []
  },
  "SpriteWidth": 18,
  "InternalName": "Swarmer"
}