{
  "Image": "Trijaw_Shark",
  "Name": "Trijaw Shark",
  "Types": [
    "NPC"
  ],
  "MaxLife": 450,
  "Defense": 23,
  "KBResist": 0.19999999,
  "Coins": 400.0,
  "Drops": [
    {
      "Name": "Shark Fin",
      "Chance": "12.5%",
      "LinkOverride": "https://terraria.wiki.gg/wiki/Shark_Fin",
      "ImageOverride": ""
    },
    {
      "Name": "Nachos",
      "Chance": "3.333%",
      "LinkOverride": "https://terraria.wiki.gg/wiki/Nachos",
      "ImageOverride": ""
    },
    {
      "Name": "Jam Sandwich",
      "Chance": "6.25%"
    },
    {
      "Name": "Ancient Riven Mask",
      "Chance": "4%"
    },
    {
      "Name": "Ancient Riven Coat",
      "Chance": "4%"
    },
    {
      "Name": "Ancient Riven Pants",
      "Chance": "4%"
    }
  ],
  "Expert": {
    "MaxLife": 900,
    "KBResist": 0.28000003,
    "Immunities": [],
    "Coins": 1000.0,
    "Drops": [
      {
        "Name": "Shark Fin",
        "Chance": "12.5%",
        "LinkOverride": "https://terraria.wiki.gg/wiki/Shark_Fin",
        "ImageOverride": ""
      },
      {
        "Name": "Nachos",
        "Chance": "3.333%",
        "LinkOverride": "https://terraria.wiki.gg/wiki/Nachos",
        "ImageOverride": ""
      },
      {
        "Name": "Jam Sandwich",
        "Chance": "6.25%"
      },
      {
        "Name": "Ancient Riven Mask",
        "Chance": "4%"
      },
      {
        "Name": "Ancient Riven Coat",
        "Chance": "4%"
      },
      {
        "Name": "Ancient Riven Pants",
        "Chance": "4%"
      }
    ]
  },
  "Master": {
    "MaxLife": 1350,
    "KBResist": 0.35999995,
    "Immunities": [],
    "Coins": 1000.0,
    "Drops": [
      {
        "Name": "Shark Fin",
        "Chance": "12.5%",
        "LinkOverride": "https://terraria.wiki.gg/wiki/Shark_Fin",
        "ImageOverride": ""
      },
      {
        "Name": "Nachos",
        "Chance": "3.333%",
        "LinkOverride": "https://terraria.wiki.gg/wiki/Nachos",
        "ImageOverride": ""
      },
      {
        "Name": "Jam Sandwich",
        "Chance": "6.25%"
      },
      {
        "Name": "Ancient Riven Mask",
        "Chance": "4%"
      },
      {
        "Name": "Ancient Riven Coat",
        "Chance": "4%"
      },
      {
        "Name": "Ancient Riven Pants",
        "Chance": "4%"
      }
    ]
  },
  "Environment": [
    "<a is=a-link image=$fromStats>Riven Hive</a>",
    "<a is=a-link image=$fromStats>Eutrophic Sea</a>",
    "<a is=a-link image=$fromStats>Riven Desert</a>",
    "<a is=a-link href=\"https://terraria.wiki.gg/wiki/Sandstorm\">Sandstorm</a>"
  ],
  "BestiaryQuotation": "This menacing shark has adapted to the Hive's ecosystem quite well, taking on a triple-mandible design used for crushing and cracking nautili caught in its path.",
  "SpriteWidth": 96,
  "InternalName": "Trijaw_Shark"
}